Workbook

Sheet Carga_de_Productos
A1: Proveedor ▼ | B1: Modelo ▼ | C1: Color ▼ | D1: Talle ▼ | E1: Stock | F1: Código de barras | G1: Nombre | H1: Categoría | I1: Colección | J1: Tipo | K1: Diseño | L1: Color | M1: Talle | N1: Costo | O1: Precio efectivo | P1: Precio transferencia | Q1: Proveedor | R1: Dirección proveedor | S1: Publicar | T1: Descripción
E2: stock | F2: barcode | G2: name | H2: category | I2: line | J2: type | K2: design | L2: color | M2: size | N2: price | O2: priceNormal | P2: priceTransfer | Q2: supplierName | R2: supplierAddress | S2: isPublic | T2: publicDescription
F3: =IF(AND(A3<>"",B3<>"",C3<>"",D3<>""),LEFT(A3,2)&LEFT(B3,4)&LEFT(C3,2)&SUBSTITUTE(UPPER(D3),"Ú","U"),"") | G3: =IFERROR(INDEX(Modelos!$B$2:$B$301,MATCH($B3,Modelos!$C$2:$C$301,0))&"","") | H3: =IFERROR(INDEX(Modelos!$D$2:$D$301,MATCH($B3,Modelos!$C$2:$C$301,0))&"","") | I3: =IFERROR(INDEX(Modelos!$E$2:$E$301,MATCH($B3,Modelos!$C$2:$C$301,0))&"","") | J3: =IFERROR(INDEX(Modelos!$F$2:$F$301,MATCH($B3,Modelos!$C$2:$C$301,0))&"","") | K3: =IFERROR(INDEX(Modelos!$G$2:$G$301,MATCH($B3,Modelos!$C$2:$C$301,0))&"","") | L3: =IFERROR(INDEX(Diccionarios!$G$2:$G$201,MATCH($C3,Diccionarios!$H$2:$H$201,0))&"","") | M3: =IF(D3="","",D3&"") | N3: =IF($B3="","",IFERROR(INDEX(Modelos!$H$2:$H$301,MATCH($B3,Modelos!$C$2:$C$301,0)),"")) | O3: =IF($B3="","",IFERROR(INDEX(Modelos!$I$2:$I$301,MATCH($B3,Modelos!$C$2:$C$301,0)),"")) | P3: =IF($B3="","",IFERROR(INDEX(Modelos!$J$2:$J$301,MATCH($B3,Modelos!$C$2:$C$301,0)),"")) | Q3: =IFERROR(INDEX(Diccionarios!$B$2:$B$201,MATCH($A3,Diccionarios!$D$2:$D$201,0))&"","") | R3: =IFERROR(INDEX(Diccionarios!$C$2:$C$201,MATCH($A3,Diccionarios!$D$2:$D$201,0))&"","") | S3: =IFERROR(INDEX(Modelos!$K$2:$K$301,MATCH($B3,Modelos!$C$2:$C$301,0))&"","") | T3: =IFERROR(INDEX(Modelos!$L$2:$L$301,MATCH($B3,Modelos!$C$2:$C$301,0))&"","")
F4: =IF(AND(A4<>"",B4<>"",C4<>"",D4<>""),LEFT(A4,2)&LEFT(B4,4)&LEFT(C4,2)&SUBSTITUTE(UPPER(D4),"Ú","U"),"") | G4: =IFERROR(INDEX(Modelos!$B$2:$B$301,MATCH($B4,Modelos!$C$2:$C$301,0))&"","") | H4: =IFERROR(INDEX(Modelos!$D$2:$D$301,MATCH($B4,Modelos!$C$2:$C$301,0))&"","") | I4: =IFERROR(INDEX(Modelos!$E$2:$E$301,MATCH($B4,Modelos!$C$2:$C$301,0))&"","") | J4: =IFERROR(INDEX(Modelos!$F$2:$F$301,MATCH($B4,Modelos!$C$2:$C$301,0))&"","") | K4: =IFERROR(INDEX(Modelos!$G$2:$G$301,MATCH($B4,Modelos!$C$2:$C$301,0))&"","") | L4: =IFERROR(INDEX(Diccionarios!$G$2:$G$201,MATCH($C4,Diccionarios!$H$2:$H$201,0))&"","") | M4: =IF(D4="","",D4&"") | N4: =IF($B4="","",IFERROR(INDEX(Modelos!$H$2:$H$301,MATCH($B4,Modelos!$C$2:$C$301,0)),"")) | O4: =IF($B4="","",IFERROR(INDEX(Modelos!$I$2:$I$301,MATCH($B4,Modelos!$C$2:$C$301,0)),"")) | P4: =IF($B4="","",IFERROR(INDEX(Modelos!$J$2:$J$301,MATCH($B4,Modelos!$C$2:$C$301,0)),"")) | Q4: =IFERROR(INDEX(Diccionarios!$B$2:$B$201,MATCH($A4,Diccionarios!$D$2:$D$201,0))&"","") | R4: =IFERROR(INDEX(Diccionarios!$C$2:$C$201,MATCH($A4,Diccionarios!$D$2:$D$201,0))&"","") | S4: =IFERROR(INDEX(Modelos!$K$2:$K$301,MATCH($B4,Modelos!$C$2:$C$301,0))&"","") | T4: =IFERROR(INDEX(Modelos!$L$2:$L$301,MATCH($B4,Modelos!$C$2:$C$301,0))&"","")
F5: =IF(AND(A5<>"",B5<>"",C5<>"",D5<>""),LEFT(A5,2)&LEFT(B5,4)&LEFT(C5,2)&SUBSTITUTE(UPPER(D5),"Ú","U"),"") | G5: =IFERROR(INDEX(Modelos!$B$2:$B$301,MATCH($B5,Modelos!$C$2:$C$301,0))&"","") | H5: =IFERROR(INDEX(Modelos!$D$2:$D$301,MATCH($B5,Modelos!$C$2:$C$301,0))&"","") | I5: =IFERROR(INDEX(Modelos!$E$2:$E$301,MATCH($B5,Modelos!$C$2:$C$301,0))&"","") | J5: =IFERROR(INDEX(Modelos!$F$2:$F$301,MATCH($B5,Modelos!$C$2:$C$301,0))&"","") | K5: =IFERROR(INDEX(Modelos!$G$2:$G$301,MATCH($B5,Modelos!$C$2:$C$301,0))&"","") | L5: =IFERROR(INDEX(Diccionarios!$G$2:$G$201,MATCH($C5,Diccionarios!$H$2:$H$201,0))&"","") | M5: =IF(D5="","",D5&"") | N5: =IF($B5="","",IFERROR(INDEX(Modelos!$H$2:$H$301,MATCH($B5,Modelos!$C$2:$C$301,0)),"")) | O5: =IF($B5="","",IFERROR(INDEX(Modelos!$I$2:$I$301,MATCH($B5,Modelos!$C$2:$C$301,0)),"")) | P5: =IF($B5="","",IFERROR(INDEX(Modelos!$J$2:$J$301,MATCH($B5,Modelos!$C$2:$C$301,0)),"")) | Q5: =IFERROR(INDEX(Diccionarios!$B$2:$B$201,MATCH($A5,Diccionarios!$D$2:$D$201,0))&"","") | R5: =IFERROR(INDEX(Diccionarios!$C$2:$C$201,MATCH($A5,Diccionarios!$D$2:$D$201,0))&"","") | S5: =IFERROR(INDEX(Modelos!$K$2:$K$301,MATCH($B5,Modelos!$C$2:$C$301,0))&"","") | T5: =IFERROR(INDEX(Modelos!$L$2:$L$301,MATCH($B5,Modelos!$C$2:$C$301,0))&"","")
F6: =IF(AND(A6<>"",B6<>"",C6<>"",D6<>""),LEFT(A6,2)&LEFT(B6,4)&LEFT(C6,2)&SUBSTITUTE(UPPER(D6),"Ú","U"),"") | G6: =IFERROR(INDEX(Modelos!$B$2:$B$301,MATCH($B6,Modelos!$C$2:$C$301,0))&"","") | H6: =IFERROR(INDEX(Modelos!$D$2:$D$301,MATCH($B6,Modelos!$C$2:$C$301,0))&"","") | I6: =IFERROR(INDEX(Modelos!$E$2:$E$301,MATCH($B6,Modelos!$C$2:$C$301,0))&"","") | J6: =IFERROR(INDEX(Modelos!$F$2:$F$301,MATCH($B6,Modelos!$C$2:$C$301,0))&"","") | K6: =IFERROR(INDEX(Modelos!$G$2:$G$301,MATCH($B6,Modelos!$C$2:$C$301,0))&"","") | L6: =IFERROR(INDEX(Diccionarios!$G$2:$G$201,MATCH($C6,Diccionarios!$H$2:$H$201,0))&"","") | M6: =IF(D6="","",D6&"") | N6: =IF($B6="","",IFERROR(INDEX(Modelos!$H$2:$H$301,MATCH($B6,Modelos!$C$2:$C$301,0)),"")) | O6: =IF($B6="","",IFERROR(INDEX(Modelos!$I$2:$I$301,MATCH($B6,Modelos!$C$2:$C$301,0)),"")) | P6: =IF($B6="","",IFERROR(INDEX(Modelos!$J$2:$J$301,MATCH($B6,Modelos!$C$2:$C$301,0)),"")) | Q6: =IFERROR(INDEX(Diccionarios!$B$2:$B$201,MATCH($A6,Diccionarios!$D$2:$D$201,0))&"","") | R6: =IFERROR(INDEX(Diccionarios!$C$2:$C$201,MATCH($A6,Diccionarios!$D$2:$D$201,0))&"","") | S6: =IFERROR(INDEX(Modelos!$K$2:$K$301,MATCH($B6,Modelos!$C$2:$C$301,0))&"","") | T6: =IFERROR(INDEX(Modelos!$L$2:$L$301,MATCH($B6,Modelos!$C$2:$C$301,0))&"","")
F7: =IF(AND(A7<>"",B7<>"",C7<>"",D7<>""),LEFT(A7,2)&LEFT(B7,4)&LEFT(C7,2)&SUBSTITUTE(UPPER(D7),"Ú","U"),"") | G7: =IFERROR(INDEX(Modelos!$B$2:$B$301,MATCH($B7,Modelos!$C$2:$C$301,0))&"","") | H7: =IFERROR(INDEX(Modelos!$D$2:$D$301,MATCH($B7,Modelos!$C$2:$C$301,0))&"","") | I7: =IFERROR(INDEX(Modelos!$E$2:$E$301,MATCH($B7,Modelos!$C$2:$C$301,0))&"","") | J7: =IFERROR(INDEX(Modelos!$F$2:$F$301,MATCH($B7,Modelos!$C$2:$C$301,0))&"","") | K7: =IFERROR(INDEX(Modelos!$G$2:$G$301,MATCH($B7,Modelos!$C$2:$C$301,0))&"","") | L7: =IFERROR(INDEX(Diccionarios!$G$2:$G$201,MATCH($C7,Diccionarios!$H$2:$H$201,0))&"","") | M7: =IF(D7="","",D7&"") | N7: =IF($B7="","",IFERROR(INDEX(Modelos!$H$2:$H$301,MATCH($B7,Modelos!$C$2:$C$301,0)),"")) | O7: =IF($B7="","",IFERROR(INDEX(Modelos!$I$2:$I$301,MATCH($B7,Modelos!$C$2:$C$301,0)),"")) | P7: =IF($B7="","",IFERROR(INDEX(Modelos!$J$2:$J$301,MATCH($B7,Modelos!$C$2:$C$301,0)),"")) | Q7: =IFERROR(INDEX(Diccionarios!$B$2:$B$201,MATCH($A7,Diccionarios!$D$2:$D$201,0))&"","") | R7: =IFERROR(INDEX(Diccionarios!$C$2:$C$201,MATCH($A7,Diccionarios!$D$2:$D$201,0))&"","") | S7: =IFERROR(INDEX(Modelos!$K$2:$K$301,MATCH($B7,Modelos!$C$2:$C$301,0))&"","") | T7: =IFERROR(INDEX(Modelos!$L$2:$L$301,MATCH($B7,Modelos!$C$2:$C$301,0))&"","")
F8: =IF(AND(A8<>"",B8<>"",C8<>"",D8<>""),LEFT(A8,2)&LEFT(B8,4)&LEFT(C8,2)&SUBSTITUTE(UPPER(D8),"Ú","U"),"") | G8: =IFERROR(INDEX(Modelos!$B$2:$B$301,MATCH($B8,Modelos!$C$2:$C$301,0))&"","") | H8: =IFERROR(INDEX(Modelos!$D$2:$D$301,MATCH($B8,Modelos!$C$2:$C$301,0))&"","") | I8: =IFERROR(INDEX(Modelos!$E$2:$E$301,MATCH($B8,Modelos!$C$2:$C$301,0))&"","") | J8: =IFERROR(INDEX(Modelos!$F$2:$F$301,MATCH($B8,Modelos!$C$2:$C$301,0))&"","") | K8: =IFERROR(INDEX(Modelos!$G$2:$G$301,MATCH($B8,Modelos!$C$2:$C$301,0))&"","") | L8: =IFERROR(INDEX(Diccionarios!$G$2:$G$201,MATCH($C8,Diccionarios!$H$2:$H$201,0))&"","") | M8: =IF(D8="","",D8&"") | N8: =IF($B8="","",IFERROR(INDEX(Modelos!$H$2:$H$301,MATCH($B8,Modelos!$C$2:$C$301,0)),"")) | O8: =IF($B8="","",IFERROR(INDEX(Modelos!$I$2:$I$301,MATCH($B8,Modelos!$C$2:$C$301,0)),"")) | P8: =IF($B8="","",IFERROR(INDEX(Modelos!$J$2:$J$301,MATCH($B8,Modelos!$C$2:$C$301,0)),"")) | Q8: =IFERROR(INDEX(Diccionarios!$B$2:$B$201,MATCH($A8,Diccionarios!$D$2:$D$201,0))&"","") | R8: =IFERROR(INDEX(Diccionarios!$C$2:$C$201,MATCH($A8,Diccionarios!$D$2:$D$201,0))&"","") | S8: =IFERROR(INDEX(Modelos!$K$2:$K$301,MATCH($B8,Modelos!$C$2:$C$301,0))&"","") | T8: =IFERROR(INDEX(Modelos!$L$2:$L$301,MATCH($B8,Modelos!$C$2:$C$301,0))&"","")
F9: =IF(AND(A9<>"",B9<>"",C9<>"",D9<>""),LEFT(A9,2)&LEFT(B9,4)&LEFT(C9,2)&SUBSTITUTE(UPPER(D9),"Ú","U"),"") | G9: =IFERROR(INDEX(Modelos!$B$2:$B$301,MATCH($B9,Modelos!$C$2:$C$301,0))&"","") | H9: =IFERROR(INDEX(Modelos!$D$2:$D$301,MATCH($B9,Modelos!$C$2:$C$301,0))&"","") | I9: =IFERROR(INDEX(Modelos!$E$2:$E$301,MATCH($B9,Modelos!$C$2:$C$301,0))&"","") | J9: =IFERROR(INDEX(Modelos!$F$2:$F$301,MATCH($B9,Modelos!$C$2:$C$301,0))&"","") | K9: =IFERROR(INDEX(Modelos!$G$2:$G$301,MATCH($B9,Modelos!$C$2:$C$301,0))&"","") | L9: =IFERROR(INDEX(Diccionarios!$G$2:$G$201,MATCH($C9,Diccionarios!$H$2:$H$201,0))&"","") | M9: =IF(D9="","",D9&"") | N9: =IF($B9="","",IFERROR(INDEX(Modelos!$H$2:$H$301,MATCH($B9,Modelos!$C$2:$C$301,0)),"")) | O9: =IF($B9="","",IFERROR(INDEX(Modelos!$I$2:$I$301,MATCH($B9,Modelos!$C$2:$C$301,0)),"")) | P9: =IF($B9="","",IFERROR(INDEX(Modelos!$J$2:$J$301,MATCH($B9,Modelos!$C$2:$C$301,0)),"")) | Q9: =IFERROR(INDEX(Diccionarios!$B$2:$B$201,MATCH($A9,Diccionarios!$D$2:$D$201,0))&"","") | R9: =IFERROR(INDEX(Diccionarios!$C$2:$C$201,MATCH($A9,Diccionarios!$D$2:$D$201,0))&"","") | S9: =IFERROR(INDEX(Modelos!$K$2:$K$301,MATCH($B9,Modelos!$C$2:$C$301,0))&"","") | T9: =IFERROR(INDEX(Modelos!$L$2:$L$301,MATCH($B9,Modelos!$C$2:$C$301,0))&"","")
F10: =IF(AND(A10<>"",B10<>"",C10<>"",D10<>""),LEFT(A10,2)&LEFT(B10,4)&LEFT(C10,2)&SUBSTITUTE(UPPER(D10),"Ú","U"),"") | G10: =IFERROR(INDEX(Modelos!$B$2:$B$301,MATCH($B10,Modelos!$C$2:$C$301,0))&"","") | H10: =IFERROR(INDEX(Modelos!$D$2:$D$301,MATCH($B10,Modelos!$C$2:$C$301,0))&"","") | I10: =IFERROR(INDEX(Modelos!$E$2:$E$301,MATCH($B10,Modelos!$C$2:$C$301,0))&"","") | J10: =IFERROR(INDEX(Modelos!$F$2:$F$301,MATCH($B10,Modelos!$C$2:$C$301,0))&"","") | K10: =IFERROR(INDEX(Modelos!$G$2:$G$301,MATCH($B10,Modelos!$C$2:$C$301,0))&"","") | L10: =IFERROR(INDEX(Diccionarios!$G$2:$G$201,MATCH($C10,Diccionarios!$H$2:$H$201,0))&"","") | M10: =IF(D10="","",D10&"") | N10: =IF($B10="","",IFERROR(INDEX(Modelos!$H$2:$H$301,MATCH($B10,Modelos!$C$2:$C$301,0)),"")) | O10: =IF($B10="","",IFERROR(INDEX(Modelos!$I$2:$I$301,MATCH($B10,Modelos!$C$2:$C$301,0)),"")) | P10: =IF($B10="","",IFERROR(INDEX(Modelos!$J$2:$J$301,MATCH($B10,Modelos!$C$2:$C$301,0)),"")) | Q10: =IFERROR(INDEX(Diccionarios!$B$2:$B$201,MATCH($A10,Diccionarios!$D$2:$D$201,0))&"","") | R10: =IFERROR(INDEX(Diccionarios!$C$2:$C$201,MATCH($A10,Diccionarios!$D$2:$D$201,0))&"","") | S10: =IFERROR(INDEX(Modelos!$K$2:$K$301,MATCH($B10,Modelos!$C$2:$C$301,0))&"","") | T10: =IFERROR(INDEX(Modelos!$L$2:$L$301,MATCH($B10,Modelos!$C$2:$C$301,0))&"","")
F11: =IF(AND(A11<>"",B11<>"",C11<>"",D11<>""),LEFT(A11,2)&LEFT(B11,4)&LEFT(C11,2)&SUBSTITUTE(UPPER(D11),"Ú","U"),"") | G11: =IFERROR(INDEX(Modelos!$B$2:$B$301,MATCH($B11,Modelos!$C$2:$C$301,0))&"","") | H11: =IFERROR(INDEX(Modelos!$D$2:$D$301,MATCH($B11,Modelos!$C$2:$C$301,0))&"","") | I11: =IFERROR(INDEX(Modelos!$E$2:$E$301,MATCH($B11,Modelos!$C$2:$C$301,0))&"","") | J11: =IFERROR(INDEX(Modelos!$F$2:$F$301,MATCH($B11,Modelos!$C$2:$C$301,0))&"","") | K11: =IFERROR(INDEX(Modelos!$G$2:$G$301,MATCH($B11,Modelos!$C$2:$C$301,0))&"","") | L11: =IFERROR(INDEX(Diccionarios!$G$2:$G$201,MATCH($C11,Diccionarios!$H$2:$H$201,0))&"","") | M11: =IF(D11="","",D11&"") | N11: =IF($B11="","",IFERROR(INDEX(Modelos!$H$2:$H$301,MATCH($B11,Modelos!$C$2:$C$301,0)),"")) | O11: =IF($B11="","",IFERROR(INDEX(Modelos!$I$2:$I$301,MATCH($B11,Modelos!$C$2:$C$301,0)),"")) | P11: =IF($B11="","",IFERROR(INDEX(Modelos!$J$2:$J$301,MATCH($B11,Modelos!$C$2:$C$301,0)),"")) | Q11: =IFERROR(INDEX(Diccionarios!$B$2:$B$201,MATCH($A11,Diccionarios!$D$2:$D$201,0))&"","") | R11: =IFERROR(INDEX(Diccionarios!$C$2:$C$201,MATCH($A11,Diccionarios!$D$2:$D$201,0))&"","") | S11: =IFERROR(INDEX(Modelos!$K$2:$K$301,MATCH($B11,Modelos!$C$2:$C$301,0))&"","") | T11: =IFERROR(INDEX(Modelos!$L$2:$L$301,MATCH($B11,Modelos!$C$2:$C$301,0))&"","")
F12: =IF(AND(A12<>"",B12<>"",C12<>"",D12<>""),LEFT(A12,2)&LEFT(B12,4)&LEFT(C12,2)&SUBSTITUTE(UPPER(D12),"Ú","U"),"") | G12: =IFERROR(INDEX(Modelos!$B$2:$B$301,MATCH($B12,Modelos!$C$2:$C$301,0))&"","") | H12: =IFERROR(INDEX(Modelos!$D$2:$D$301,MATCH($B12,Modelos!$C$2:$C$301,0))&"","") | I12: =IFERROR(INDEX(Modelos!$E$2:$E$301,MATCH($B12,Modelos!$C$2:$C$301,0))&"","") | J12: =IFERROR(INDEX(Modelos!$F$2:$F$301,MATCH($B12,Modelos!$C$2:$C$301,0))&"","") | K12: =IFERROR(INDEX(Modelos!$G$2:$G$301,MATCH($B12,Modelos!$C$2:$C$301,0))&"","") | L12: =IFERROR(INDEX(Diccionarios!$G$2:$G$201,MATCH($C12,Diccionarios!$H$2:$H$201,0))&"","") | M12: =IF(D12="","",D12&"") | N12: =IF($B12="","",IFERROR(INDEX(Modelos!$H$2:$H$301,MATCH($B12,Modelos!$C$2:$C$301,0)),"")) | O12: =IF($B12="","",IFERROR(INDEX(Modelos!$I$2:$I$301,MATCH($B12,Modelos!$C$2:$C$301,0)),"")) | P12: =IF($B12="","",IFERROR(INDEX(Modelos!$J$2:$J$301,MATCH($B12,Modelos!$C$2:$C$301,0)),"")) | Q12: =IFERROR(INDEX(Diccionarios!$B$2:$B$201,MATCH($A12,Diccionarios!$D$2:$D$201,0))&"","") | R12: =IFERROR(INDEX(Diccionarios!$C$2:$C$201,MATCH($A12,Diccionarios!$D$2:$D$201,0))&"","") | S12: =IFERROR(INDEX(Modelos!$K$2:$K$301,MATCH($B12,Modelos!$C$2:$C$301,0))&"","") | T12: =IFERROR(INDEX(Modelos!$L$2:$L$301,MATCH($B12,Modelos!$C$2:$C$301,0))&"","")
F13: =IF(AND(A13<>"",B13<>"",C13<>"",D13<>""),LEFT(A13,2)&LEFT(B13,4)&LEFT(C13,2)&SUBSTITUTE(UPPER(D13),"Ú","U"),"") | G13: =IFERROR(INDEX(Modelos!$B$2:$B$301,MATCH($B13,Modelos!$C$2:$C$301,0))&"","") | H13: =IFERROR(INDEX(Modelos!$D$2:$D$301,MATCH($B13,Modelos!$C$2:$C$301,0))&"","") | I13: =IFERROR(INDEX(Modelos!$E$2:$E$301,MATCH($B13,Modelos!$C$2:$C$301,0))&"","") | J13: =IFERROR(INDEX(Modelos!$F$2:$F$301,MATCH($B13,Modelos!$C$2:$C$301,0))&"","") | K13: =IFERROR(INDEX(Modelos!$G$2:$G$301,MATCH($B13,Modelos!$C$2:$C$301,0))&"","") | L13: =IFERROR(INDEX(Diccionarios!$G$2:$G$201,MATCH($C13,Diccionarios!$H$2:$H$201,0))&"","") | M13: =IF(D13="","",D13&"") | N13: =IF($B13="","",IFERROR(INDEX(Modelos!$H$2:$H$301,MATCH($B13,Modelos!$C$2:$C$301,0)),"")) | O13: =IF($B13="","",IFERROR(INDEX(Modelos!$I$2:$I$301,MATCH($B13,Modelos!$C$2:$C$301,0)),"")) | P13: =IF($B13="","",IFERROR(INDEX(Modelos!$J$2:$J$301,MATCH($B13,Modelos!$C$2:$C$301,0)),"")) | Q13: =IFERROR(INDEX(Diccionarios!$B$2:$B$201,MATCH($A13,Diccionarios!$D$2:$D$201,0))&"","") | R13: =IFERROR(INDEX(Diccionarios!$C$2:$C$201,MATCH($A13,Diccionarios!$D$2:$D$201,0))&"","") | S13: =IFERROR(INDEX(Modelos!$K$2:$K$301,MATCH($B13,Modelos!$C$2:$C$301,0))&"","") | T13: =IFERROR(INDEX(Modelos!$L$2:$L$301,MATCH($B13,Modelos!$C$2:$C$301,0))&"","")
F14: =IF(AND(A14<>"",B14<>"",C14<>"",D14<>""),LEFT(A14,2)&LEFT(B14,4)&LEFT(C14,2)&SUBSTITUTE(UPPER(D14),"Ú","U"),"") | G14: =IFERROR(INDEX(Modelos!$B$2:$B$301,MATCH($B14,Modelos!$C$2:$C$301,0))&"","") | H14: =IFERROR(INDEX(Modelos!$D$2:$D$301,MATCH($B14,Modelos!$C$2:$C$301,0))&"","") | I14: =IFERROR(INDEX(Modelos!$E$2:$E$301,MATCH($B14,Modelos!$C$2:$C$301,0))&"","") | J14: =IFERROR(INDEX(Modelos!$F$2:$F$301,MATCH($B14,Modelos!$C$2:$C$301,0))&"","") | K14: =IFERROR(INDEX(Modelos!$G$2:$G$301,MATCH($B14,Modelos!$C$2:$C$301,0))&"","") | L14: =IFERROR(INDEX(Diccionarios!$G$2:$G$201,MATCH($C14,Diccionarios!$H$2:$H$201,0))&"","") | M14: =IF(D14="","",D14&"") | N14: =IF($B14="","",IFERROR(INDEX(Modelos!$H$2:$H$301,MATCH($B14,Modelos!$C$2:$C$301,0)),"")) | O14: =IF($B14="","",IFERROR(INDEX(Modelos!$I$2:$I$301,MATCH($B14,Modelos!$C$2:$C$301,0)),"")) | P14: =IF($B14="","",IFERROR(INDEX(Modelos!$J$2:$J$301,MATCH($B14,Modelos!$C$2:$C$301,0)),"")) | Q14: =IFERROR(INDEX(Diccionarios!$B$2:$B$201,MATCH($A14,Diccionarios!$D$2:$D$201,0))&"","") | R14: =IFERROR(INDEX(Diccionarios!$C$2:$C$201,MATCH($A14,Diccionarios!$D$2:$D$201,0))&"","") | S14: =IFERROR(INDEX(Modelos!$K$2:$K$301,MATCH($B14,Modelos!$C$2:$C$301,0))&"","") | T14: =IFERROR(INDEX(Modelos!$L$2:$L$301,MATCH($B14,Modelos!$C$2:$C$301,0))&"","")
... F502: =IF(AND(A502<>"",B502<>"",C502<>"",D502<>""),LEFT(A502,2)&LEFT(B502,4)&LEFT(C502,2)&SUBSTITUTE(UPPER(D502),"Ú","U"),"") | G502: =IFERROR(INDEX(Modelos!$B$2:$B$301,MATCH($B502,Modelos!$C$2:$C$301,0))&"","") | H502: =IFERROR(INDEX(Modelos!$D$2:$D$301,MATCH($B502,Modelos!$C$2:$C$301,0))&"","") | I502: =IFERROR(INDEX(Modelos!$E$2:$E$301,MATCH($B502,Modelos!$C$2:$C$301,0))&"","") | J502: =IFERROR(INDEX(Modelos!$F$2:$F$301,MATCH($B502,Modelos!$C$2:$C$301,0))&"","") | K502: =IFERROR(INDEX(Modelos!$G$2:$G$301,MATCH($B502,Modelos!$C$2:$C$301,0))&"","") | L502: =IFERROR(INDEX(Diccionarios!$G$2:$G$201,MATCH($C502,Diccionarios!$H$2:$H$201,0))&"","") | M502: =IF(D502="","",D502&"") | N502: =IF($B502="","",IFERROR(INDEX(Modelos!$H$2:$H$301,MATCH($B502,Modelos!$C$2:$C$301,0)),"")) | O502: =IF($B502="","",IFERROR(INDEX(Modelos!$I$2:$I$301,MATCH($B502,Modelos!$C$2:$C$301,0)),"")) | P502: =IF($B502="","",IFERROR(INDEX(Modelos!$J$2:$J$301,MATCH($B502,Modelos!$C$2:$C$301,0)),"")) | Q502: =IFERROR(INDEX(Diccionarios!$B$2:$B$201,MATCH($A502,Diccionarios!$D$2:$D$201,0))&"","") | R502: =IFERROR(INDEX(Diccionarios!$C$2:$C$201,MATCH($A502,Diccionarios!$D$2:$D$201,0))&"","") | S502: =IFERROR(INDEX(Modelos!$K$2:$K$301,MATCH($B502,Modelos!$C$2:$C$301,0))&"","") | T502: =IFERROR(INDEX(Modelos!$L$2:$L$301,MATCH($B502,Modelos!$C$2:$C$301,0))&"","")

Sheet Modelos
A1: Código (4 dígitos) | B1: Nombre del modelo (así se ve en la tienda) | C1: Opción (auto) | D1: Categoría | E1: Colección | F1: Tipo | G1: Diseño | H1: Costo | I1: Precio efectivo | J1: Precio transferencia | K1: Publicar en tienda | L1: Descripción para la tienda (una vez por modelo)
A2: 0001 | B2: Jean Clásico | C2: =IF(OR(A2="",B2=""),"",A2&" - "&B2) -> 0001 - Jean Clásico | D2: Jeans | E2: Urbano | F2: Recto
A3: 0002 | B3: Jean Mom | C3: =IF(OR(A3="",B3=""),"",A3&" - "&B3) -> 0002 - Jean Mom | D3: Jeans | E3: Urbano | F3: Mom
A4: 0003 | B4: Remera Oversize | C4: =IF(OR(A4="",B4=""),"",A4&" - "&B4) -> 0003 - Remera Oversize | D4: Remeras | E4: Urbano | F4: Oversize
A5: 0004 | B5: Remera Básica | C5: =IF(OR(A5="",B5=""),"",A5&" - "&B5) -> 0004 - Remera Básica | D5: Remeras | E5: Urbano | F5: Regular
A6: 0005 | B6: Buzo Canguro | C6: =IF(OR(A6="",B6=""),"",A6&" - "&B6) -> 0005 - Buzo Canguro | D6: Buzos | E6: Urbano | F6: Hoodie
A7: 0006 | B7: Remera Oversize Essential | C7: =IF(OR(A7="",B7=""),"",A7&" - "&B7) -> 0006 - Remera Oversize Essential | D7: Remeras | E7: Urbano | F7: Oversize | G7: Logo | H7: 12500 | I7: 28000 | J7: 25200 | K7: Sí | L7: Remera oversize de algodón peinado 24/1, calce amplio y hombro caído. Logo BairesYa estampado en el pecho.
A8: 0007 | B8: Calza Deportiva Tiro Alto | C8: =IF(OR(A8="",B8=""),"",A8&" - "&B8) -> 0007 - Calza Deportiva Tiro Alto | D8: Pantalones | E8: Deportivo | F8: Calza | G8: Lisa | H8: 15000 | I8: 36000 | J8: 32400 | K8: Sí | L8: Calza de lycra suplex con cintura alta y efecto compresión. No transparenta.
A9: 0008 | B9: Blazer Sastrero | C9: =IF(OR(A9="",B9=""),"",A9&" - "&B9) -> 0008 - Blazer Sastrero | D9: Sastrería | E9: Formal | F9: Blazer | G9: Liso | H9: 54000 | I9: 115000 | J9: 103500 | K9: Sí | L9: Blazer entallado con botones al frente. Va con el pantalón sastrero o con jean y zapatillas.
C10: =IF(OR(A10="",B10=""),"",A10&" - "&B10)
C11: =IF(OR(A11="",B11=""),"",A11&" - "&B11)
C12: =IF(OR(A12="",B12=""),"",A12&" - "&B12)
C13: =IF(OR(A13="",B13=""),"",A13&" - "&B13)
C14: =IF(OR(A14="",B14=""),"",A14&" - "&B14)
C15: =IF(OR(A15="",B15=""),"",A15&" - "&B15)
C16: =IF(OR(A16="",B16=""),"",A16&" - "&B16)
C17: =IF(OR(A17="",B17=""),"",A17&" - "&B17)
C18: =IF(OR(A18="",B18=""),"",A18&" - "&B18)
C19: =IF(OR(A19="",B19=""),"",A19&" - "&B19)
C20: =IF(OR(A20="",B20=""),"",A20&" - "&B20)
C21: =IF(OR(A21="",B21=""),"",A21&" - "&B21)
... C301: =IF(OR(A301="",B301=""),"",A301&" - "&B301)

Sheet Diccionarios
A1: Cód. proveedor | B1: Proveedor | C1: Dirección del proveedor | D1: Opción (auto) | F1: Cód. color | G1: Color | H1: Opción (auto) | J1: Talles | L1: Categorías | N1: Colecciones | P1: Publicar
A2: 01 | B2: Taverniti | C2: Av. Avellaneda 3000 | D2: =IF(OR(A2="",B2=""),"",A2&" - "&B2) -> 01 - Taverniti | F2: 01 | G2: Azul | H2: =IF(OR(F2="",G2=""),"",F2&" - "&G2) -> 01 - Azul | J2: XS | L2: Remeras | N2: Deportivo | P2: Sí
A3: 02 | B3: Levis | D3: =IF(OR(A3="",B3=""),"",A3&" - "&B3) -> 02 - Levis | F3: 02 | G3: Negro | H3: =IF(OR(F3="",G3=""),"",F3&" - "&G3) -> 02 - Negro | J3: S | L3: Camisas | N3: Urbano | P3: No
A4: 03 | B4: MarcaLocal | D4: =IF(OR(A4="",B4=""),"",A4&" - "&B4) -> 03 - MarcaLocal | F4: 03 | G4: Blanco | H4: =IF(OR(F4="",G4=""),"",F4&" - "&G4) -> 03 - Blanco | J4: M | L4: Buzos | N4: Formal
A5: 99 | B5: Genérico | D5: =IF(OR(A5="",B5=""),"",A5&" - "&B5) -> 99 - Genérico | F5: 04 | G5: Gris | H5: =IF(OR(F5="",G5=""),"",F5&" - "&G5) -> 04 - Gris | J5: L | L5: Camperas
D6: =IF(OR(A6="",B6=""),"",A6&" - "&B6) | F6: 05 | G6: Rojo | H6: =IF(OR(F6="",G6=""),"",F6&" - "&G6) -> 05 - Rojo | J6: XL | L6: Jeans
D7: =IF(OR(A7="",B7=""),"",A7&" - "&B7) | F7: 06 | G7: Verde | H7: =IF(OR(F7="",G7=""),"",F7&" - "&G7) -> 06 - Verde | J7: XXL | L7: Pantalones
D8: =IF(OR(A8="",B8=""),"",A8&" - "&B8) | F8: 07 | G8: Azul marino | H8: =IF(OR(F8="",G8=""),"",F8&" - "&G8) -> 07 - Azul marino | J8: Único | L8: Shorts
D9: =IF(OR(A9="",B9=""),"",A9&" - "&B9) | F9: 08 | G9: Azul jean | H9: =IF(OR(F9="",G9=""),"",F9&" - "&G9) -> 08 - Azul jean | J9: 30 | L9: Sastrería
D10: =IF(OR(A10="",B10=""),"",A10&" - "&B10) | F10: 09 | G10: Celeste | H10: =IF(OR(F10="",G10=""),"",F10&" - "&G10) -> 09 - Celeste | J10: 32 | L10: Accesorios
D11: =IF(OR(A11="",B11=""),"",A11&" - "&B11) | F11: 10 | G11: Beige | H11: =IF(OR(F11="",G11=""),"",F11&" - "&G11) -> 10 - Beige | J11: 34
D12: =IF(OR(A12="",B12=""),"",A12&" - "&B12) | F12: 11 | G12: Gris melange | H12: =IF(OR(F12="",G12=""),"",F12&" - "&G12) -> 11 - Gris melange | J12: 36
D13: =IF(OR(A13="",B13=""),"",A13&" - "&B13) | F13: 12 | G13: Verde militar | H13: =IF(OR(F13="",G13=""),"",F13&" - "&G13) -> 12 - Verde militar | J13: 38
D14: =IF(OR(A14="",B14=""),"",A14&" - "&B14) | F14: 13 | G14: Bordó | H14: =IF(OR(F14="",G14=""),"",F14&" - "&G14) -> 13 - Bordó | J14: 40
D15: =IF(OR(A15="",B15=""),"",A15&" - "&B15) | F15: 99 | G15: Varios | H15: =IF(OR(F15="",G15=""),"",F15&" - "&G15) -> 99 - Varios | J15: 42
D16: =IF(OR(A16="",B16=""),"",A16&" - "&B16) | H16: =IF(OR(F16="",G16=""),"",F16&" - "&G16) | J16: 44
D17: =IF(OR(A17="",B17=""),"",A17&" - "&B17) | H17: =IF(OR(F17="",G17=""),"",F17&" - "&G17) | J17: 46
D18: =IF(OR(A18="",B18=""),"",A18&" - "&B18) | H18: =IF(OR(F18="",G18=""),"",F18&" - "&G18)
D19: =IF(OR(A19="",B19=""),"",A19&" - "&B19) | H19: =IF(OR(F19="",G19=""),"",F19&" - "&G19)
D20: =IF(OR(A20="",B20=""),"",A20&" - "&B20) | H20: =IF(OR(F20="",G20=""),"",F20&" - "&G20)
D21: =IF(OR(A21="",B21=""),"",A21&" - "&B21) | H21: =IF(OR(F21="",G21=""),"",F21&" - "&G21)
D22: =IF(OR(A22="",B22=""),"",A22&" - "&B22) | H22: =IF(OR(F22="",G22=""),"",F22&" - "&G22)
D23: =IF(OR(A23="",B23=""),"",A23&" - "&B23) | H23: =IF(OR(F23="",G23=""),"",F23&" - "&G23)
D24: =IF(OR(A24="",B24=""),"",A24&" - "&B24) | H24: =IF(OR(F24="",G24=""),"",F24&" - "&G24)
D25: =IF(OR(A25="",B25=""),"",A25&" - "&B25) | H25: =IF(OR(F25="",G25=""),"",F25&" - "&G25)
D26: =IF(OR(A26="",B26=""),"",A26&" - "&B26) | H26: =IF(OR(F26="",G26=""),"",F26&" - "&G26)
D27: =IF(OR(A27="",B27=""),"",A27&" - "&B27) | H27: =IF(OR(F27="",G27=""),"",F27&" - "&G27)
D28: =IF(OR(A28="",B28=""),"",A28&" - "&B28) | H28: =IF(OR(F28="",G28=""),"",F28&" - "&G28)
D29: =IF(OR(A29="",B29=""),"",A29&" - "&B29) | H29: =IF(OR(F29="",G29=""),"",F29&" - "&G29)
... D201: =IF(OR(A201="",B201=""),"",A201&" - "&B201) | H201: =IF(OR(F201="",G201=""),"",F201&" - "&G201)

Sheet Instrucciones
B1: Cómo cargar productos en BairesYa
B3: Pasos
B4: 1. Diccionarios | C4: Cargá una vez los proveedores, colores, talles y categorías. Los códigos de proveedor (2 dígitos) y color (2 dígitos) forman parte del código de barras.
B5: 2. Modelos | C5: Cargá cada prenda una sola vez: nombre, categoría, colección, precios, si se publica en la tienda y la descripción. Todos sus talles y colores toman estos datos: la descripción se escribe una sola vez acá.
B6: 3. Carga_de_Productos | C6: Una fila por cada combinación de talle y color: elegí Proveedor, Modelo, Color y Talle de las listas y escribí el Stock. Las columnas grises se completan solas.
B7: 4. Importar | C7: Guardá el archivo y subilo en el panel: Importar Excel. Antes de confirmar vas a ver una vista previa con lo que se crea, lo que se actualiza y los errores.
B9: Reglas
B10: Código de barras | C10: Proveedor (2) + Modelo (4) + Color (2) + Talle. Ej: 01 + 0003 + 02 + M = 01000302M. No cambies los códigos ya usados: cambiaría el código de barras de esos productos.
B11: Nombre del modelo | C11: La tienda agrupa en una sola ficha los productos con el mismo nombre (muestra los talles y colores disponibles). Usá siempre el mismo nombre para todas las variantes.
B12: Si el código ya existe | C12: El producto se actualiza con los datos del archivo y el stock se reemplaza por el de la fila (Stock vacío = 0).
B13: Precio distinto en una variante | C13: En Carga_de_Productos, escribí el número encima de la fórmula en esa fila (por ejemplo, un talle XXL más caro).
B14: Publicar en tienda | C14: Sí: el modelo se ve en la tienda. No: queda oculto. Vacío: no cambia; los productos nuevos quedan ocultos, salvo que el modelo ya esté publicado.
B15: Descripción | C15: Se muestra en la ficha del producto. Si está vacía no borra la que ya tiene el producto. Una variante nueva de un modelo ya cargado toma la descripción del modelo.
B16: Columnas que no estén | C16: Si borrás una columna de la hoja, la importación no modifica ese dato en los productos existentes.
B17: Límites | C17: Hasta 2000 filas por archivo. Descripción de hasta 2000 caracteres.
B18: Fotos | C18: Nombrá cada foto con el código de barras (columna F) + .jpg, por ejemplo 01000302M.jpg (portada). Para más fotos del mismo producto: 01000302M_2.jpg … _8. Juntalas en una carpeta y subilas con el script de fotos (npm run fotos). También se pueden subir de a una desde el inventario del panel. Sin foto, la tienda muestra el logo de BairesYa.
B19: Listas | C19: Cargá las opciones de Diccionarios y Modelos sin dejar filas vacías en el medio, así aparecen en las listas desplegables.
B21: Columnas de importación
B22: Clave (fila 2) | C22: Qué es
B23: barcode * | C23: Código de barras único del producto (obligatorio).
B24: name * | C24: Nombre del modelo (obligatorio).
B25: category | C25: Categoría: Remeras, Jeans, Buzos…
B26: line | C26: Colección: Deportivo, Urbano o Formal.
B27: type / design | C27: Tipo (Oversize, Mom, Hoodie…) y diseño (Liso, Logo…). Se muestran en la ficha.
B28: color / size | C28: Color y talle de la variante.
B29: price | C29: Costo. No se muestra en la tienda ni a los empleados.
B30: priceNormal / priceTransfer | C30: Precio de venta en efectivo y por transferencia.
B31: stock | C31: Cantidad en stock. Reemplaza la actual.
B32: supplierName / supplierAddress | C32: Proveedor y su dirección (aparecen en la lista de compras).
B33: isPublic | C33: Publicar en la tienda: Sí o No.
B34: publicDescription | C34: Descripción para la tienda.
C35: Si armás tu propio Excel, alcanza con que una de las primeras 5 filas tenga estas claves como encabezado.
